sofascore_wrapper/__init__.py
sofascore_wrapper/american_football.py
sofascore_wrapper/api.py
sofascore_wrapper/baseball.py
sofascore_wrapper/basketball.py
sofascore_wrapper/cricket.py
sofascore_wrapper/esports.py
sofascore_wrapper/flag.py
sofascore_wrapper/ice_hockey.py
sofascore_wrapper/league.py
sofascore_wrapper/manager.py
sofascore_wrapper/match.py
sofascore_wrapper/mma.py
sofascore_wrapper/motorsport.py
sofascore_wrapper/news.py
sofascore_wrapper/player.py
sofascore_wrapper/rugby.py
sofascore_wrapper/search.py
sofascore_wrapper/team.py
sofascore_wrapper/tennis.py
sofascore_wrapper/transfers.py
sofascore_wrapper/user_data.py
sofascore_wrapper/tools/enums.json
sofascore_wrapper-1.0.24.dist-info/licenses/LICENSE
sofascore_wrapper-1.0.24.dist-info/METADATA
sofascore_wrapper-1.0.24.dist-info/WHEEL
sofascore_wrapper-1.0.24.dist-info/top_level.txt
sofascore_wrapper-1.0.24.dist-info/RECORD
